{
  "formatVersion": 1,
  "database": {
    "version": 1,
    "identityHash": "1b08f0ee973a1a924fc6cd6f6f773e74",
    "entities": [
      {
        "tableName": "User",
        "createSql": "CREATE TABLE IF NOT EXISTS `${TABLE_NAME}` (`uid` INTEGER NOT NULL, `id` INTEGER, `name` TEXT, `email` TEXT, `password` TEXT, `email_verified_at` TEXT, `created_at` TEXT, `updated_at` TEXT, PRIMARY KEY(`uid`))",
        "fields": [
          {
            "fieldPath": "uid",
            "columnName": "uid",
            "affinity": "INTEGER",
            "notNull": true
          },
          {
            "fieldPath": "id",
            "columnName": "id",
            "affinity": "INTEGER",
            "notNull": false
          },
          {
            "fieldPath": "name",
            "columnName": "name",
            "affinity": "TEXT",
            "notNull": false
          },
          {
            "fieldPath": "email",
            "columnName": "email",
            "affinity": "TEXT",
            "notNull": false
          },
          {
            "fieldPath": "password",
            "columnName": "password",
            "affinity": "TEXT",
            "notNull": false
          },
          {
            "fieldPath": "email_verified_at",
            "columnName": "email_verified_at",
            "affinity": "TEXT",
            "notNull": false
          },
          {
            "fieldPath": "created_at",
            "columnName": "created_at",
            "affinity": "TEXT",
            "notNull": false
          },
          {
            "fieldPath": "updated_at",
            "columnName": "updated_at",
            "affinity": "TEXT",
            "notNull": false
          }
        ],
        "primaryKey": {
          "columnNames": [
            "uid"
          ],
          "autoGenerate": false
        },
        "indices": [],
        "foreignKeys": []
      },
      {
        "tableName": "Quote",
        "createSql": "CREATE TABLE IF NOT EXISTS `${TABLE_NAME}` (`id` INTEGER NOT NULL, `quote` TEXT NOT NULL, `author` TEXT NOT NULL, `thumbnail` TEXT NOT NULL, `created_at` TEXT NOT NULL, `updated_at` TEXT NOT NULL, PRIMARY KEY(`id`))",
        "fields": [
          {
            "fieldPath": "id",
            "columnName": "id",
            "affinity": "INTEGER",
            "notNull": true
          },
          {
            "fieldPath": "quote",
            "columnName": "quote",
            "affinity": "TEXT",
            "notNull": true
          },
          {
            "fieldPath": "author",
            "columnName": "author",
            "affinity": "TEXT",
            "notNull": true
          },
          {
            "fieldPath": "thumbnail",
            "columnName": "thumbnail",
            "affinity": "TEXT",
            "notNull": true
          },
          {
            "fieldPath": "created_at",
            "columnName": "created_at",
            "affinity": "TEXT",
            "notNull": true
          },
          {
            "fieldPath": "updated_at",
            "columnName": "updated_at",
            "affinity": "TEXT",
            "notNull": true
          }
        ],
        "primaryKey": {
          "columnNames": [
            "id"
          ],
          "autoGenerate": false
        },
        "indices": [],
        "foreignKeys": []
      }
    ],
    "views": [],
    "setupQueries": [
      "CREATE TABLE IF NOT EXISTS room_master_table (id INTEGER PRIMARY KEY,identity_hash TEXT)",
      "INSERT OR REPLACE INTO room_master_table (id,identity_hash) VALUES(42, '1b08f0ee973a1a924fc6cd6f6f773e74')"
    ]
  }
}